directlfq/__init__.py
directlfq/_modidx.py
directlfq/_nbdev.py
directlfq/benchmarking.py
directlfq/cli.py
directlfq/config.py
directlfq/dashboard_parts.py
directlfq/gui.py
directlfq/gui_textfields.py
directlfq/lfq_manager.py
directlfq/normalization.py
directlfq/protein_intensity_estimation.py
directlfq/test_utils.py
directlfq/testfile_handling.py
directlfq/tracefilter.py
directlfq/utils.py
directlfq/utils_fileread.py
directlfq/visualizations.py
directlfq/configs/download_links_for_testfiles_all.yaml
directlfq/configs/download_links_for_testfiles_quicktest.yaml
directlfq/configs/intable_config.yaml
directlfq/configs/interface_parameters.json
directlfq/configs/spectronaut_tableconfig_fragion.rs
directlfq/configs/spectronaut_tableconfig_precursor.rs
directlfq/configs/spectronaut_tableconfig_ptm_fragion.rs
directlfq/docs/Empty_manual.pdf
directlfq/img/github.png
directlfq/img/max-planck-gesellschaft.jpg
directlfq/img/mpi_logo.png
directlfq/img/ms_pipeline_visualization.png
directlfq/style/dashboard_style.css
directlfq-0.3.2.dist-info/licenses/LICENSE
release/pyinstaller/directlfq_pyinstaller.py
requirements/requirements.txt
requirements/requirements_dask.txt
requirements/requirements_dask_loose.txt
requirements/requirements_development.txt
requirements/requirements_gui.txt
requirements/requirements_gui_loose.txt
requirements/requirements_loose.txt
requirements/requirements_tests.txt
tests/download_testfiles.py
tests/test_cli.py
tests/test_gui.py
tests/pytest/test_requirements.py
tests/runtime_tests/profile_execution_time.py
tests/runtime_tests/test_runtime_on_dataset.py
directlfq-0.3.2.dist-info/METADATA
directlfq-0.3.2.dist-info/WHEEL
directlfq-0.3.2.dist-info/entry_points.txt
directlfq-0.3.2.dist-info/top_level.txt
directlfq-0.3.2.dist-info/RECORD
