Metadata-Version: 2.4
Name: directlfq
Version: 0.3.2
Summary: An open-source Python package of the AlphaPept ecosystem
Author-email: Mann Labs <opensource@alphapept.com>
Project-URL: Paper, https://doi.org/10.1016/j.mcpro.2023.100581
Project-URL: Repository, https://github.com/MannLabs/directlfq
Project-URL: Issues, https://github.com/MannLabs/directlfq/issues
Project-URL: Mann Labs Homepage, https://www.biochem.mpg.de/mann
Keywords: LFQ,label-free quantification,mass spectrometry,proteomics,bioinformatics,AlphaPept,AlphaPept ecosystem
Classifier: Development Status :: 5 - Production/Stable
Classifier: Intended Audience :: Science/Research
Classifier: License :: OSI Approved :: Apache Software License
Classifier: Operating System :: OS Independent
Classifier: Programming Language :: Python :: 3
Classifier: Topic :: Scientific/Engineering :: Bio-Informatics
Requires-Python: >=3.9
License-File: LICENSE
Requires-Dist: numpy
Requires-Dist: pandas
Requires-Dist: numba
Requires-Dist: multiprocess
Requires-Dist: pyarrow
Provides-Extra: stable
Requires-Dist: numpy==1.23.5; extra == "stable"
Requires-Dist: pandas==2.2.3; extra == "stable"
Requires-Dist: numba==0.56.4; extra == "stable"
Requires-Dist: multiprocess==0.70.14; extra == "stable"
Requires-Dist: pyarrow==17.0.0; extra == "stable"
Provides-Extra: gui
Requires-Dist: panel; extra == "gui"
Requires-Dist: dash; extra == "gui"
Requires-Dist: matplotlib; extra == "gui"
Provides-Extra: gui-stable
Requires-Dist: panel==1.4.5; extra == "gui-stable"
Requires-Dist: dash==2.18.1; extra == "gui-stable"
Requires-Dist: matplotlib==3.9.2; extra == "gui-stable"
Provides-Extra: dask
Requires-Dist: dask; extra == "dask"
Provides-Extra: dask-stable
Requires-Dist: dask==2024.8.0; extra == "dask-stable"
Provides-Extra: tests
Requires-Dist: matplotlib_venn; extra == "tests"
Requires-Dist: matplotlib; extra == "tests"
Requires-Dist: wget; extra == "tests"
Requires-Dist: seaborn; extra == "tests"
Requires-Dist: nbdev>=2.3.9; extra == "tests"
Requires-Dist: alphabase>=1.5.0; extra == "tests"
Requires-Dist: progressbar; extra == "tests"
Requires-Dist: pytest; extra == "tests"
Requires-Dist: nbmake==1.5.3; extra == "tests"
Provides-Extra: development
Requires-Dist: jupyter; extra == "development"
Requires-Dist: jupyter_contrib_nbextensions; extra == "development"
Requires-Dist: autodocsumm; extra == "development"
Requires-Dist: sphinx-rtd-theme; extra == "development"
Requires-Dist: bump-my-version; extra == "development"
Requires-Dist: pipdeptree; extra == "development"
Requires-Dist: ipykernel; extra == "development"
Requires-Dist: notebook; extra == "development"
Requires-Dist: matplotlib_venn; extra == "development"
Requires-Dist: matplotlib; extra == "development"
Requires-Dist: wget; extra == "development"
Requires-Dist: seaborn; extra == "development"
Requires-Dist: nbdev>=2.3.9; extra == "development"
Requires-Dist: alphabase>=1.5.0; extra == "development"
Requires-Dist: progressbar; extra == "development"
Requires-Dist: pytest; extra == "development"
Requires-Dist: nbmake==1.5.3; extra == "development"
Dynamic: license-file
